{
    "data": {
        "repository": {
            "issues": {
                "totalCount": 23484,
                "nodes": [
                    {
                        "title": "ResourceHttpRequestHandlerTests.modified() fails on Windows due to millisecond precision [SPR-7565]",
                        "url": "https://github.com/spring-projects/spring-framework/issues/12222",
                        "createdAt": "2010-09-17T05:10:00Z",
                        "closedAt": "2012-06-19T03:43:19Z"
                    },
                    {
                        "title": "Exception when @Scheduled and @Async placed on one bean [SPR-7566]",
                        "url": "https://github.com/spring-projects/spring-framework/issues/12223",
                        "createdAt": "2010-09-17T07:24:40Z",
                        "closedAt": "2018-12-26T16:51:33Z"
                    },
                    {
                        "title": "Parameter annotations such as @RequestParam not applied from an interface [SPR-7567]",
                        "url": "https://github.com/spring-projects/spring-framework/issues/12224",
                        "createdAt": "2010-09-17T11:26:13Z",
                        "closedAt": "2019-01-12T03:32:17Z"
                    },
                    {
                        "title": "BeanFactoryAdvisorRetrievalHelper.findAdvisorBeans() must not include ancestors when discovering advisors [SPR-7568]",
                        "url": "https://github.com/spring-projects/spring-framework/issues/12225",
                        "createdAt": "2010-09-18T02:44:37Z",
                        "closedAt": "2018-12-26T17:22:16Z"
                    },
                    {
                        "title": "TypeDescriptor unable to dynamically resolve the type of nested collections [SPR-7569]",
                        "url": "https://github.com/spring-projects/spring-framework/issues/12226",
                        "createdAt": "2010-09-18T09:53:54Z",
                        "closedAt": "2015-09-22T17:34:30Z"
                    },
                    {
                        "title": "AspectJExpressionPointcut does not use the right classloader when initializing the pointcut parser [SPR-7570]",
                        "url": "https://github.com/spring-projects/spring-framework/issues/12227",
                        "createdAt": "2010-09-19T02:13:11Z",
                        "closedAt": "2012-06-19T03:43:26Z"
                    },
                    {
                        "title": "since expressions in javadoc [SPR-7571]",
                        "url": "https://github.com/spring-projects/spring-framework/issues/12228",
                        "createdAt": "2010-09-19T05:40:29Z",
                        "closedAt": "2018-12-28T10:24:04Z"
                    },
                    {
                        "title": "LocalSessionFactoryBean persist initial entities after creating database schema [SPR-7572]",
                        "url": "https://github.com/spring-projects/spring-framework/issues/12229",
                        "createdAt": "2010-09-19T13:47:56Z",
                        "closedAt": "2018-12-28T09:59:38Z"
                    },
                    {
                        "title": "Publish updated spring-mvc.xsd with resources element definition [SPR-7573]",
                        "url": "https://github.com/spring-projects/spring-framework/issues/12230",
                        "createdAt": "2010-09-20T03:04:06Z",
                        "closedAt": "2012-06-19T02:28:08Z"
                    },
                    {
                        "title": "PropertyPlaceholderHelper#findPlaceholderEndIndex does not work for custom placeholderPrefix [SPR-7574]",
                        "url": "https://github.com/spring-projects/spring-framework/issues/12231",
                        "createdAt": "2010-09-20T04:36:24Z",
                        "closedAt": "2012-06-19T03:43:13Z"
                    },
                    {
                        "title": "script Groovy, unable to refresh it under Webapps context [SPR-7575]",
                        "url": "https://github.com/spring-projects/spring-framework/issues/12232",
                        "createdAt": "2010-09-20T06:56:45Z",
                        "closedAt": "2010-09-20T23:29:39Z"
                    },
                    {
                        "title": "Add support for bootsrapping for log4j init outside web container [SPR-7576]",
                        "url": "https://github.com/spring-projects/spring-framework/issues/12233",
                        "createdAt": "2010-09-20T13:04:31Z",
                        "closedAt": "2018-12-26T08:36:09Z"
                    },
                    {
                        "title": "Support for JDK 7's concurrency and collections updates (JSR-166y) [SPR-7578]",
                        "url": "https://github.com/spring-projects/spring-framework/issues/12234",
                        "createdAt": "2010-09-21T00:16:49Z",
                        "closedAt": "2013-03-04T02:36:36Z"
                    },
                    {
                        "title": "Support for JDK 7's JDBC 4.1 (JSR-TBD) [SPR-7579]",
                        "url": "https://github.com/spring-projects/spring-framework/issues/12235",
                        "createdAt": "2010-09-21T00:19:10Z",
                        "closedAt": "2013-03-04T02:35:58Z"
                    },
                    {
                        "title": "Spring Quartz- Pending Jobs are not getting triggered in the order they were scheduled [SPR-7580]",
                        "url": "https://github.com/spring-projects/spring-framework/issues/12236",
                        "createdAt": "2010-09-21T11:04:23Z",
                        "closedAt": "2019-01-12T03:32:15Z"
                    },
                    {
                        "title": "AnnotationSessionFactoryBean postProcessConfiguration() should not be final [SPR-7581]",
                        "url": "https://github.com/spring-projects/spring-framework/issues/12237",
                        "createdAt": "2010-09-21T13:03:05Z",
                        "closedAt": "2012-06-19T03:43:22Z"
                    },
                    {
                        "title": "ProxyFactoryBean getObject called before setInterceptorNames, silently creating an invalid proxy [SPR-7582]",
                        "url": "https://github.com/spring-projects/spring-framework/issues/12238",
                        "createdAt": "2010-09-21T15:29:13Z",
                        "closedAt": "2021-12-14T16:02:47Z"
                    },
                    {
                        "title": "RestTemplate.put returns void [SPR-7583]",
                        "url": "https://github.com/spring-projects/spring-framework/issues/12239",
                        "createdAt": "2010-09-21T15:33:30Z",
                        "closedAt": "2015-08-06T12:59:00Z"
                    },
                    {
                        "title": "Migration from 2.5.6 to 3.0.2 - Lazy Init functions differently. [SPR-7584]",
                        "url": "https://github.com/spring-projects/spring-framework/issues/12240",
                        "createdAt": "2010-09-21T16:34:03Z",
                        "closedAt": "2018-12-26T16:07:00Z"
                    },
                    {
                        "title": "URI/URL Related Improvement Suggestions for RequestMapping in Spring MVC [SPR-7585]",
                        "url": "https://github.com/spring-projects/spring-framework/issues/12241",
                        "createdAt": "2010-09-21T22:09:54Z",
                        "closedAt": "2012-12-13T08:51:11Z"
                    },
                    {
                        "title": "View returned from @ExceptionHandler does not take into account response content type [SPR-7586]",
                        "url": "https://github.com/spring-projects/spring-framework/issues/12242",
                        "createdAt": "2010-09-22T14:23:57Z",
                        "closedAt": "2012-06-19T03:43:52Z"
                    },
                    {
                        "title": "Editable id attribute of form input fields with freemarker macros [SPR-7587]",
                        "url": "https://github.com/spring-projects/spring-framework/issues/12243",
                        "createdAt": "2010-09-23T06:05:17Z",
                        "closedAt": "2018-12-28T12:03:03Z"
                    },
                    {
                        "title": "LazyConnectionDataSourceProxy does not return thread-safe Connection handles [SPR-7588]",
                        "url": "https://github.com/spring-projects/spring-framework/issues/12244",
                        "createdAt": "2010-09-23T18:44:35Z",
                        "closedAt": "2015-09-22T17:34:39Z"
                    },
                    {
                        "title": "Determination of the best pattern match to map a handler to an URL [SPR-7589]",
                        "url": "https://github.com/spring-projects/spring-framework/issues/12245",
                        "createdAt": "2010-09-24T01:34:57Z",
                        "closedAt": "2014-05-05T10:05:58Z"
                    },
                    {
                        "title": "@RequestParam fails when ConfigurableWebBindingInitializer has both messageCodesResolver and conversionService [SPR-7590]",
                        "url": "https://github.com/spring-projects/spring-framework/issues/12246",
                        "createdAt": "2010-09-24T01:38:15Z",
                        "closedAt": "2012-06-19T03:44:04Z"
                    },
                    {
                        "title": "HttpStatusCodeException should contain response body [SPR-7591]",
                        "url": "https://github.com/spring-projects/spring-framework/issues/12247",
                        "createdAt": "2010-09-24T02:59:20Z",
                        "closedAt": "2012-06-19T03:43:28Z"
                    },
                    {
                        "title": "Add JavaScript support for Spring dynamic languages [SPR-7592]",
                        "url": "https://github.com/spring-projects/spring-framework/issues/12248",
                        "createdAt": "2010-09-24T11:24:57Z",
                        "closedAt": "2015-04-01T11:48:33Z"
                    },
                    {
                        "title": "Spring 3.0's PropertyPlaceholderConfigurer processes colons as default value separator [SPR-7593]",
                        "url": "https://github.com/spring-projects/spring-framework/issues/12249",
                        "createdAt": "2010-09-26T14:59:31Z",
                        "closedAt": "2011-12-12T19:21:17Z"
                    },
                    {
                        "title": "@InitBinder not called before @Controller method execution [SPR-7594]",
                        "url": "https://github.com/spring-projects/spring-framework/issues/12250",
                        "createdAt": "2010-09-27T04:15:03Z",
                        "closedAt": "2010-09-29T07:52:28Z"
                    },
                    {
                        "title": "Add ability to add to beginning of TestExecutionListener list in TestContextManager [SPR-7595]",
                        "url": "https://github.com/spring-projects/spring-framework/issues/12251",
                        "createdAt": "2010-09-27T08:49:54Z",
                        "closedAt": "2012-06-19T03:42:58Z"
                    },
                    {
                        "title": "Allow org.springframework.core.convert.TypeDescriptor to be subclassed [SPR-7596]",
                        "url": "https://github.com/spring-projects/spring-framework/issues/12252",
                        "createdAt": "2010-09-27T09:08:10Z",
                        "closedAt": "2012-12-10T16:49:42Z"
                    },
                    {
                        "title": "Construct org.springframework.core.convert.TypeDescriptor programatically for collections [SPR-7597]",
                        "url": "https://github.com/spring-projects/spring-framework/issues/12253",
                        "createdAt": "2010-09-27T09:28:44Z",
                        "closedAt": "2012-06-19T03:43:39Z"
                    },
                    {
                        "title": "StringUtils#parseLocaleString(String) with Variant when no Country [SPR-7598]",
                        "url": "https://github.com/spring-projects/spring-framework/issues/12254",
                        "createdAt": "2010-09-28T08:25:09Z",
                        "closedAt": "2018-07-26T08:09:31Z"
                    },
                    {
                        "title": "Provide proper @Value documentation in the reference documentation [SPR-7599]",
                        "url": "https://github.com/spring-projects/spring-framework/issues/12255",
                        "createdAt": "2010-09-28T08:35:45Z",
                        "closedAt": "2019-06-10T09:48:12Z"
                    },
                    {
                        "title": "[regression] JMS-131: Session is closed exception in 3.0.5 snapshot [SPR-7600]",
                        "url": "https://github.com/spring-projects/spring-framework/issues/12256",
                        "createdAt": "2010-09-28T13:32:28Z",
                        "closedAt": "2010-09-29T03:19:26Z"
                    },
                    {
                        "title": "NullPointerException if there's no script for jdbc:embedded-database [SPR-7601]",
                        "url": "https://github.com/spring-projects/spring-framework/issues/12257",
                        "createdAt": "2010-09-29T06:12:49Z",
                        "closedAt": "2010-10-15T14:57:46Z"
                    },
                    {
                        "title": "Embedded database support in trouble shutting down Derby [SPR-7602]",
                        "url": "https://github.com/spring-projects/spring-framework/issues/12258",
                        "createdAt": "2010-09-29T06:35:35Z",
                        "closedAt": "2013-12-23T11:22:01Z"
                    },
                    {
                        "title": "NPE in AbstractPollingMessageListenerContainer when committing transaction after message receive timeout [SPR-7603]",
                        "url": "https://github.com/spring-projects/spring-framework/issues/12259",
                        "createdAt": "2010-09-30T04:34:56Z",
                        "closedAt": "2012-06-19T02:28:20Z"
                    },
                    {
                        "title": "jdbc:datasource lacks 'name' attribute or related mechanism [SPR-7604]",
                        "url": "https://github.com/spring-projects/spring-framework/issues/12260",
                        "createdAt": "2010-09-30T05:50:29Z",
                        "closedAt": "2015-09-22T17:17:48Z"
                    },
                    {
                        "title": "SessionFactoryUtils.doGetSession creates new session holder without JTA transaction [SPR-7605]",
                        "url": "https://github.com/spring-projects/spring-framework/issues/12261",
                        "createdAt": "2010-09-30T07:37:56Z",
                        "closedAt": "2018-12-27T11:03:48Z"
                    },
                    {
                        "title": "Spring 3.0.2.RELEASE breaks classpath settings in manifest.mf [SPR-7606]",
                        "url": "https://github.com/spring-projects/spring-framework/issues/12262",
                        "createdAt": "2010-09-30T08:28:29Z",
                        "closedAt": "2018-12-28T11:48:42Z"
                    },
                    {
                        "title": "When a bean definition is overridden, detect whether the definition has changed and log accordingly [SPR-7607]",
                        "url": "https://github.com/spring-projects/spring-framework/issues/12263",
                        "createdAt": "2010-09-30T11:07:56Z",
                        "closedAt": "2015-05-26T01:15:24Z"
                    },
                    {
                        "title": "@PathVariable and @ModelAttribute incompatibility prevent me from having a nice \"update\" handler [SPR-7608]",
                        "url": "https://github.com/spring-projects/spring-framework/issues/12264",
                        "createdAt": "2010-09-30T13:27:07Z",
                        "closedAt": "2012-06-19T03:43:15Z"
                    },
                    {
                        "title": "Correct typos - Chapter 21. JMS [SPR-7609]",
                        "url": "https://github.com/spring-projects/spring-framework/issues/12265",
                        "createdAt": "2010-09-30T19:39:26Z",
                        "closedAt": "2012-06-19T03:43:50Z"
                    },
                    {
                        "title": "ClassUtils.isAssignable should be commutative for wrapper and primitive types [SPR-7610]",
                        "url": "https://github.com/spring-projects/spring-framework/issues/12266",
                        "createdAt": "2010-10-01T07:53:25Z",
                        "closedAt": "2012-06-19T03:43:03Z"
                    },
                    {
                        "title": "Provide a way to use a native JDBC extractor for metadata processing in SimpleJdbcInsert [SPR-7611]",
                        "url": "https://github.com/spring-projects/spring-framework/issues/12267",
                        "createdAt": "2010-10-01T11:41:26Z",
                        "closedAt": "2012-06-19T03:43:02Z"
                    },
                    {
                        "title": "Proposed solution to streaming blob data quandry with JdbcTemplate [SPR-7612]",
                        "url": "https://github.com/spring-projects/spring-framework/issues/12268",
                        "createdAt": "2010-10-03T08:44:06Z",
                        "closedAt": "2018-12-28T10:37:06Z"
                    },
                    {
                        "title": "Enable ability to specify interface types in Jdbc4NativeJdbcExtractor [SPR-7613]",
                        "url": "https://github.com/spring-projects/spring-framework/issues/12269",
                        "createdAt": "2010-10-03T09:53:04Z",
                        "closedAt": "2012-06-19T03:44:10Z"
                    },
                    {
                        "title": "SpEL: Resolving values from Map works different after PropertyAccessor is cached [SPR-7614]",
                        "url": "https://github.com/spring-projects/spring-framework/issues/12270",
                        "createdAt": "2010-10-03T11:09:27Z",
                        "closedAt": "2012-06-19T03:42:50Z"
                    },
                    {
                        "title": "BeanFactory.getType()  returning NULL for bean of type ProxyFactoryBean  [SPR-7615]",
                        "url": "https://github.com/spring-projects/spring-framework/issues/12271",
                        "createdAt": "2010-10-03T23:32:02Z",
                        "closedAt": "2015-09-22T17:34:30Z"
                    },
                    {
                        "title": "ApplicationEventMulticaster does not support @Order [SPR-7616]",
                        "url": "https://github.com/spring-projects/spring-framework/issues/12272",
                        "createdAt": "2010-10-04T05:42:16Z",
                        "closedAt": "2012-05-26T05:14:47Z"
                    },
                    {
                        "title": "Add utility to ValidationUtils that converts a Set of 303 ContraintViolations to Errors [SPR-7617]",
                        "url": "https://github.com/spring-projects/spring-framework/issues/12273",
                        "createdAt": "2010-10-04T14:16:51Z",
                        "closedAt": "2015-09-22T17:34:31Z"
                    },
                    {
                        "title": "Additional event on destroying beans after failed initialization [SPR-7618]",
                        "url": "https://github.com/spring-projects/spring-framework/issues/12274",
                        "createdAt": "2010-10-05T04:08:39Z",
                        "closedAt": "2018-12-28T11:53:38Z"
                    },
                    {
                        "title": "Make MappingJacksonJsonView fields protected to make extending it easier [SPR-7619]",
                        "url": "https://github.com/spring-projects/spring-framework/issues/12275",
                        "createdAt": "2010-10-05T09:09:41Z",
                        "closedAt": "2013-02-08T13:24:51Z"
                    },
                    {
                        "title": "StaxEventContentHandler does not set Location for StartDocument event [SPR-7620]",
                        "url": "https://github.com/spring-projects/spring-framework/issues/12276",
                        "createdAt": "2010-10-05T10:37:48Z",
                        "closedAt": "2012-06-19T03:43:39Z"
                    },
                    {
                        "title": "AbstractStaxContentHandler sets NamespaceContext on every start/end element [SPR-7621]",
                        "url": "https://github.com/spring-projects/spring-framework/issues/12277",
                        "createdAt": "2010-10-05T12:05:53Z",
                        "closedAt": "2012-06-19T03:39:33Z"
                    },
                    {
                        "title": "PropertyOverrideConfigurer turns 'ref' properties into 'value' properties [SPR-7622]",
                        "url": "https://github.com/spring-projects/spring-framework/issues/12278",
                        "createdAt": "2010-10-05T19:18:29Z",
                        "closedAt": "2015-09-22T17:34:39Z"
                    },
                    {
                        "title": "SybaseMaxValueIncrementer doesn't work with non-enterprise Sybase db [SPR-7623]",
                        "url": "https://github.com/spring-projects/spring-framework/issues/12279",
                        "createdAt": "2010-10-07T06:24:51Z",
                        "closedAt": "2012-06-19T03:39:49Z"
                    },
                    {
                        "title": "EJB3's @TransactionManagement should be able to use as meta-annotation, just as  @Transactional is. [SPR-7624]",
                        "url": "https://github.com/spring-projects/spring-framework/issues/12280",
                        "createdAt": "2010-10-07T07:34:45Z",
                        "closedAt": "2018-12-26T16:57:25Z"
                    },
                    {
                        "title": "Wrong pom.xml checksum on maven repository [SPR-7625]",
                        "url": "https://github.com/spring-projects/spring-framework/issues/12281",
                        "createdAt": "2010-10-07T10:45:33Z",
                        "closedAt": "2014-05-26T05:50:03Z"
                    },
                    {
                        "title": "Auto proxying does not seem to work for interfaces with \"generices\" parameter types [SPR-7626]",
                        "url": "https://github.com/spring-projects/spring-framework/issues/12282",
                        "createdAt": "2010-10-07T12:23:06Z",
                        "closedAt": "2018-12-28T11:30:28Z"
                    },
                    {
                        "title": "add Serializer/Deserializer strategy interfaces and default implementation [SPR-7627]",
                        "url": "https://github.com/spring-projects/spring-framework/issues/12283",
                        "createdAt": "2010-10-07T14:58:45Z",
                        "closedAt": "2012-06-19T03:39:12Z"
                    },
                    {
                        "title": "@Bean cannot be used on static factory methods but error message does not inform of you of that [SPR-7628]",
                        "url": "https://github.com/spring-projects/spring-framework/issues/12284",
                        "createdAt": "2010-10-07T16:31:56Z",
                        "closedAt": "2012-06-19T03:39:04Z"
                    },
                    {
                        "title": "NullPointerException in error path of ConstructorResolver when constructing a @Bean from a factory method [SPR-7629]",
                        "url": "https://github.com/spring-projects/spring-framework/issues/12285",
                        "createdAt": "2010-10-07T16:40:16Z",
                        "closedAt": "2012-06-19T03:39:25Z"
                    },
                    {
                        "title": "Major performance slowdown in AnnotationUtils.findAnnotation [SPR-7630]",
                        "url": "https://github.com/spring-projects/spring-framework/issues/12286",
                        "createdAt": "2010-10-08T01:04:42Z",
                        "closedAt": "2018-03-31T12:24:51Z"
                    },
                    {
                        "title": "SpEL: Conversion of collection method parameters fails [SPR-7631]",
                        "url": "https://github.com/spring-projects/spring-framework/issues/12287",
                        "createdAt": "2010-10-08T06:41:35Z",
                        "closedAt": "2012-06-19T03:39:51Z"
                    },
                    {
                        "title": "Allow valid file extension paths for content negotiation to be specified [SPR-7632]",
                        "url": "https://github.com/spring-projects/spring-framework/issues/12288",
                        "createdAt": "2010-10-08T07:43:18Z",
                        "closedAt": "2016-09-08T12:59:17Z"
                    },
                    {
                        "title": "Spring EL method resolver fails on vararg calls [SPR-7633]",
                        "url": "https://github.com/spring-projects/spring-framework/issues/12289",
                        "createdAt": "2010-10-08T07:54:04Z",
                        "closedAt": "2012-06-19T03:39:34Z"
                    },
                    {
                        "title": "Refactor SimpleJdbcInsert/Call to make it easier to provide custom meta data providers [SPR-7634]",
                        "url": "https://github.com/spring-projects/spring-framework/issues/12290",
                        "createdAt": "2010-10-08T11:59:53Z",
                        "closedAt": "2015-09-22T18:20:31Z"
                    },
                    {
                        "title": "Unresolved thread safety issue in AutowiredAnnotationBeanPostProcessor.AutowiredMethodElement [SPR-7635]",
                        "url": "https://github.com/spring-projects/spring-framework/issues/12291",
                        "createdAt": "2010-10-09T22:13:58Z",
                        "closedAt": "2012-06-19T03:39:21Z"
                    },
                    {
                        "title": "XStreamMarshaller - Add support for configuring XStream with aliases by class (type) and also defining multiple attributes for the same class. [SPR-7636]",
                        "url": "https://github.com/spring-projects/spring-framework/issues/12292",
                        "createdAt": "2010-10-10T05:32:32Z",
                        "closedAt": "2012-06-19T03:39:53Z"
                    },
                    {
                        "title": "ExceptinHandler method behaves differently than request handler [SPR-7637]",
                        "url": "https://github.com/spring-projects/spring-framework/issues/12293",
                        "createdAt": "2010-10-10T07:29:36Z",
                        "closedAt": "2012-06-19T03:39:39Z"
                    },
                    {
                        "title": "spring:eval causes SpelEvaluationException when page is opened in second user-session [SPR-7638]",
                        "url": "https://github.com/spring-projects/spring-framework/issues/12294",
                        "createdAt": "2010-10-10T14:40:01Z",
                        "closedAt": "2012-06-19T02:28:16Z"
                    },
                    {
                        "title": "A resolved placeholder in an alias field isn't split into multiple aliases [SPR-7639]",
                        "url": "https://github.com/spring-projects/spring-framework/issues/12295",
                        "createdAt": "2010-10-10T17:00:35Z",
                        "closedAt": "2015-09-22T17:34:33Z"
                    },
                    {
                        "title": "Problam while render Tiles [SPR-7640]",
                        "url": "https://github.com/spring-projects/spring-framework/issues/12296",
                        "createdAt": "2010-10-11T00:02:46Z",
                        "closedAt": "2010-12-16T11:04:19Z"
                    },
                    {
                        "title": "List in \"15.3.2.3 Supported handler method arguments and return types\" is incomplete [SPR-7641]",
                        "url": "https://github.com/spring-projects/spring-framework/issues/12297",
                        "createdAt": "2010-10-11T04:30:20Z",
                        "closedAt": "2012-06-19T03:39:08Z"
                    },
                    {
                        "title": "Thread safety issue in InjectionMetaData affecting setter methods annotated with @Resource tags [SPR-7642]",
                        "url": "https://github.com/spring-projects/spring-framework/issues/12298",
                        "createdAt": "2010-10-11T06:08:22Z",
                        "closedAt": "2012-06-19T03:39:55Z"
                    },
                    {
                        "title": "EhCacheFactoryBean doesn't read defaults from defaultCache [SPR-7643]",
                        "url": "https://github.com/spring-projects/spring-framework/issues/12299",
                        "createdAt": "2010-10-11T09:38:58Z",
                        "closedAt": "2015-09-22T17:34:38Z"
                    },
                    {
                        "title": "mapping a parameter with a Dot [SPR-7644]",
                        "url": "https://github.com/spring-projects/spring-framework/issues/12300",
                        "createdAt": "2010-10-11T12:21:20Z",
                        "closedAt": "2018-12-28T10:34:46Z"
                    },
                    {
                        "title": "Provide support for Http Client 4 now that it is available [SPR-7645]",
                        "url": "https://github.com/spring-projects/spring-framework/issues/12301",
                        "createdAt": "2010-10-11T13:03:37Z",
                        "closedAt": "2011-02-07T02:22:18Z"
                    },
                    {
                        "title": "DateTimeZoneHandlerInterceptor that resolves current JodaTimeContext from Cookie [SPR-7646]",
                        "url": "https://github.com/spring-projects/spring-framework/issues/12302",
                        "createdAt": "2010-10-11T13:07:42Z",
                        "closedAt": "2018-12-28T11:05:27Z"
                    },
                    {
                        "title": "ObjectToStringConverter check is too limited [SPR-7647]",
                        "url": "https://github.com/spring-projects/spring-framework/issues/12303",
                        "createdAt": "2010-10-11T20:27:49Z",
                        "closedAt": "2015-09-22T16:49:59Z"
                    },
                    {
                        "title": "Property support for form:options title [SPR-7648]",
                        "url": "https://github.com/spring-projects/spring-framework/issues/12304",
                        "createdAt": "2010-10-12T09:03:33Z",
                        "closedAt": "2015-09-22T17:34:31Z"
                    },
                    {
                        "title": "JpaExceptionTranslatorAspect is applied by default (without requiring @Repository) [SPR-7649]",
                        "url": "https://github.com/spring-projects/spring-framework/issues/12305",
                        "createdAt": "2010-10-12T22:26:22Z",
                        "closedAt": "2012-05-16T01:23:57Z"
                    },
                    {
                        "title": "NPE in DefaultMessageListenerContainer while committing and no message was received [SPR-7650]",
                        "url": "https://github.com/spring-projects/spring-framework/issues/12306",
                        "createdAt": "2010-10-13T02:01:33Z",
                        "closedAt": "2012-06-19T03:25:14Z"
                    },
                    {
                        "title": "Support for SpEL as a scripting language usable with Hibernate Validator 4.1 @ScriptAssert [SPR-7651]",
                        "url": "https://github.com/spring-projects/spring-framework/issues/12307",
                        "createdAt": "2010-10-13T10:29:44Z",
                        "closedAt": null
                    },
                    {
                        "title": "SpEl does not support conjunction (&&) and disjunction (||) logic [SPR-7652]",
                        "url": "https://github.com/spring-projects/spring-framework/issues/12308",
                        "createdAt": "2010-10-13T10:31:13Z",
                        "closedAt": "2016-09-19T19:24:16Z"
                    },
                    {
                        "title": "Ability to render a single error message across a group of fields [SPR-7653]",
                        "url": "https://github.com/spring-projects/spring-framework/issues/12309",
                        "createdAt": "2010-10-13T11:47:17Z",
                        "closedAt": "2018-12-28T11:58:45Z"
                    },
                    {
                        "title": "Overloaded @PathVariable based handler methods fail with ambiguity when URL mapping is specified in XML [SPR-7654]",
                        "url": "https://github.com/spring-projects/spring-framework/issues/12310",
                        "createdAt": "2010-10-13T13:15:31Z",
                        "closedAt": "2012-12-12T13:43:02Z"
                    },
                    {
                        "title": "Support declarative SQL script execution in the TestContext framework [SPR-7655]",
                        "url": "https://github.com/spring-projects/spring-framework/issues/12311",
                        "createdAt": "2010-10-14T08:42:04Z",
                        "closedAt": "2014-07-18T10:16:40Z"
                    },
                    {
                        "title": "'default-merge' attribute value does not propagate to collection elements [SPR-7656]",
                        "url": "https://github.com/spring-projects/spring-framework/issues/12312",
                        "createdAt": "2010-10-14T09:52:13Z",
                        "closedAt": "2012-06-19T03:39:48Z"
                    },
                    {
                        "title": "StringToCollectionConverter does not trim parsed collection elements [SPR-7657]",
                        "url": "https://github.com/spring-projects/spring-framework/issues/12313",
                        "createdAt": "2010-10-14T10:59:21Z",
                        "closedAt": "2012-06-19T03:39:41Z"
                    },
                    {
                        "title": "SqlParameter name lower case conversion in CallMetaDataContext causes error. [SPR-7658]",
                        "url": "https://github.com/spring-projects/spring-framework/issues/12314",
                        "createdAt": "2010-10-15T01:47:55Z",
                        "closedAt": "2012-06-19T03:39:37Z"
                    },
                    {
                        "title": "MockHttpSession methods should throw IllegalStateException if invalid [SPR-7659]",
                        "url": "https://github.com/spring-projects/spring-framework/issues/12315",
                        "createdAt": "2010-10-15T03:19:20Z",
                        "closedAt": "2013-07-24T10:17:04Z"
                    },
                    {
                        "title": "Allow for XSD validation in OXM [SPR-7660]",
                        "url": "https://github.com/spring-projects/spring-framework/issues/12316",
                        "createdAt": "2010-10-15T04:19:54Z",
                        "closedAt": "2015-09-22T18:20:32Z"
                    },
                    {
                        "title": "AbstractJasperReportsView uses request locale directly instead of relying on LocaleContext infrastructure [SPR-7661]",
                        "url": "https://github.com/spring-projects/spring-framework/issues/12317",
                        "createdAt": "2010-10-18T02:00:44Z",
                        "closedAt": "2015-09-22T17:34:31Z"
                    },
                    {
                        "title": "Add multipart request support to portlet resource requests [SPR-7662]",
                        "url": "https://github.com/spring-projects/spring-framework/issues/12318",
                        "createdAt": "2010-10-18T08:31:59Z",
                        "closedAt": "2015-09-22T17:34:31Z"
                    },
                    {
                        "title": "More informative Resource.toString(), like its URL - helps when AppContext displays resources it was loaded from (can display full URL) [SPR-7663]",
                        "url": "https://github.com/spring-projects/spring-framework/issues/12319",
                        "createdAt": "2010-10-19T02:00:56Z",
                        "closedAt": "2015-09-22T17:34:32Z"
                    },
                    {
                        "title": "Incorrect handling of annotation attached to interface method [SPR-7664]",
                        "url": "https://github.com/spring-projects/spring-framework/issues/12320",
                        "createdAt": "2010-10-19T04:42:18Z",
                        "closedAt": "2012-02-26T05:10:14Z"
                    },
                    {
                        "title": "autowire-candidate=\"false\" for scanned components [SPR-7665]",
                        "url": "https://github.com/spring-projects/spring-framework/issues/12321",
                        "createdAt": "2010-10-19T13:46:20Z",
                        "closedAt": "2018-12-28T10:55:53Z"
                    }
                ],
                "pageInfo": {
                    "endCursor": "Y3Vyc29yOnYyOpHOF7qmJg==",
                    "hasNextPage": true
                }
            }
        }
    }
}